package za.ac.tut.comicnovel;

public class ComicNovel {

    private String title;
    private int volume;
    private String code;

    public ComicNovel(String string, int i, String string1) {
        // <editor-fold defaultstate="collapsed" desc="Compiled Code">
        /* 0: aload_0
         * 1: invokespecial #1                  // Method java/lang/Object."<init>":()V
         * 4: aload_0
         * 5: aload_1
         * 6: putfield      #2                  // Field title:Ljava/lang/String;
         * 9: aload_0
         * 10: iload_2
         * 11: putfield      #3                  // Field volume:I
         * 14: aload_0
         * 15: aload_3
         * 16: putfield      #4                  // Field code:Ljava/lang/String;
         * 19: return
         *  */
        // </editor-fold>
    }

    public String getTitle() {
        // <editor-fold defaultstate="collapsed" desc="Compiled Code">
        /* 0: aload_0
         * 1: getfield      #2                  // Field title:Ljava/lang/String;
         * 4: areturn
         *  */
        // </editor-fold>
    }

    public int getVolume() {
        // <editor-fold defaultstate="collapsed" desc="Compiled Code">
        /* 0: aload_0
         * 1: getfield      #3                  // Field volume:I
         * 4: ireturn
         *  */
        // </editor-fold>
    }

    public String getCode() {
        // <editor-fold defaultstate="collapsed" desc="Compiled Code">
        /* 0: aload_0
         * 1: getfield      #4                  // Field code:Ljava/lang/String;
         * 4: areturn
         *  */
        // </editor-fold>
    }
}
